fav/urls.py
fav/admin.py
fav/views.py
fav/__init__.py
fav/tests.py
fav/forms.py
fav/models.py
fav/templatetags/__init__.py
fav/templatetags/favorite_tags.py
fav/migrations/0009_favorite_count.py
fav/migrations/0006_remove_favorite_count.py
fav/migrations/0012_auto_20160111_1231.py
fav/migrations/__init__.py
fav/migrations/0001_initial.py
fav/migrations/0007_favorite_count.py
fav/migrations/0003_auto_20150914_1158.py
fav/migrations/0011_favorite_cookie.py
fav/migrations/0004_remove_favorite_favorited.py
fav/migrations/0008_remove_favorite_count.py
fav/migrations/0005_favorite_count.py
fav/migrations/0002_auto_20150914_1133.py
fav/migrations/0010_remove_favorite_count.py
fav/static/js/jquery.js
fav/static/js/fav.js
fav/templates/fav/fav_count.html
fav/templates/fav/fav_form.html
django_ajax_favorite-1.0.0.dev1.dist-info/WHEEL
django_ajax_favorite-1.0.0.dev1.dist-info/RECORD
django_ajax_favorite-1.0.0.dev1.dist-info/top_level.txt
django_ajax_favorite-1.0.0.dev1.dist-info/metadata.json
django_ajax_favorite-1.0.0.dev1.dist-info/DESCRIPTION.rst
django_ajax_favorite-1.0.0.dev1.dist-info/METADATA
test_app/urls.py
test_app/admin.py
test_app/views.py
test_app/__init__.py
test_app/tests.py
test_app/models.py
test_app/migrations/__init__.py
test_app/migrations/0001_initial.py
